{
  "folderStructure": {
    "name": "My Computer",
    "children": [
      {
        "name": "3½ Floppy (A:)",
        "children": []
      },
      {
        "name": "Local Disk (C:)",
        "children": [
          {
            "name": "Documents and Settings",
            "children": []
          },
          {
            "name": "Inetpub",
            "children": [
              { "name": "AdminScripts", "children": [] },
              {
                "name": "wwwroot",
                "children": [
                  { "name": "company", "children": [] },
                  { "name": "downloads", "children": [] },
                  { "name": "images", "children": [] },
                  { "name": "news", "children": [] },
                  { "name": "scripts", "children": [] },
                  { "name": "support", "children": [] }
                ]
              }
            ]
          },
          { "name": "mysql", "children": [] },
          { "name": "PHP", "children": [] },
          { "name": "Program Files", "children": [] },
          { "name": "WINDOWS", "children": [] }
        ]
      }
    ]
  }
}
